lcep_package/__init__.py
lcep_package/cli.py
lcep_package/data/test.tsv
lcep_package/models/model_08.04.2021_v2.xgb
lcep_package/models/model_28.08.2020_v1.xgb
lcep_package-2.0.1.dist-info/AUTHORS.rst
lcep_package-2.0.1.dist-info/LICENSE
lcep_package-2.0.1.dist-info/METADATA
lcep_package-2.0.1.dist-info/WHEEL
lcep_package-2.0.1.dist-info/entry_points.txt
lcep_package-2.0.1.dist-info/top_level.txt
lcep_package-2.0.1.dist-info/RECORD
