Metadata-Version: 2.1
Name: lcep-package
Version: 2.0.1
Summary: Python package for lcep.
Home-page: https://github.com/mlf-core/lcep-package
Author: Lukas Heumos
Author-email: lukas.heumos@posteo.net
License: MIT
Keywords: lcep-package
Platform: UNKNOWN
Classifier: Development Status :: 2 - Pre-Alpha
Classifier: Intended Audience :: Developers
Classifier: License :: OSI Approved :: MIT License
Classifier: Natural Language :: English
Classifier: Programming Language :: Python :: 3
Classifier: Programming Language :: Python :: 3.7
Classifier: Programming Language :: Python :: 3.8
Requires-Python: >=3.7
Requires-Dist: rich (>=9.1.0)
Requires-Dist: click (>=7.1.2)
Requires-Dist: xgboost (==1.2.1)
Requires-Dist: numpy (==1.19.1)
